pydantic_mql/__init__.py
pydantic_mql/condition.py
pydantic_mql/util.py
pydantic_mql/eval/__init__.py
pydantic_mql/eval/operator.py
pydantic_mql/sql/__init__.py
pydantic_mql-0.1.0.dist-info/LICENSE
pydantic_mql-0.1.0.dist-info/METADATA
pydantic_mql-0.1.0.dist-info/WHEEL
pydantic_mql-0.1.0.dist-info/top_level.txt
pydantic_mql-0.1.0.dist-info/RECORD
