Metadata-Version: 2.1
Name: pydantic-mql
Version: 0.1.0
Home-page: https://github.com/rkhullar/python-libraries/tree/main/pydantic-mql
Author: Rajan Khullar
Author-email: rkhullar03@gmail.com
License: MIT NON-AI
Requires-Python: ~=3.11
License-File: LICENSE
Requires-Dist: pydantic ~=2.0
